{
  "ticker_map": {
    "NVDA":    "NVDA_US_EQ",
    "AAPL":    "AAPL_US_EQ",
    "AMD":     "AMD_US_EQ",
    "MSFT":    "MSFT_US_EQ",
    "AMZN":    "AMZN_US_EQ",
    "TSLA":    "TSLA_US_EQ",
    "PLTR":    "PLTR_US_EQ",
    "META":    "FB_US_EQ",
    "GOOGL":   "GOOGL_US_EQ",
    "ASML":    "ASML_US_EQ",
    "IBM":     "IBM_US_EQ",
    "VWCE.AS": "VWCEd_EQ",
    "VUSA.L":  "VUSAl_EQ",
    "VUKE.L":  "VUKEl_EQ",
    "LLY":     "LLY_US_EQ",
    "ISRG":    "ISRG_US_EQ",
    "JPM":     "JPM_US_EQ",
    "COST":    "COST_US_EQ",
    "NKE":     "NKE_US_EQ",
    "HON":     "HON_US_EQ",
    "CAT":     "CAT_US_EQ",
    "GS":      "GS_US_EQ",
    "V":       "V_US_EQ",
    "XOM":     "XOM_US_EQ",
    "UNH":     "UNH_US_EQ",
    "HPQ":     "HPQ_US_EQ",
    "DELL":    "DELL_US_EQ",
    "CRM":     "CRM_US_EQ",
    "ORCL":    "ORCL_US_EQ",
    "INTC":    "INTC_US_EQ",
    "AZN.L":   "AZNl_EQ",
    "SHEL.L":  "SHELl_EQ",
    "HSBA.L":  "HSBAl_EQ",
    "SPCX":    "SPCX_US_EQ",
    "DHR":     "DHR_US_EQ",
    "TMO":     "TMO_US_EQ",
    "DE":      "DE_US_EQ",
    "INTU":    "INTU_US_EQ",
    "HD":      "HD_US_EQ",
    "AMGN":    "AMGN_US_EQ",
    "JNJ":     "JNJ_US_EQ",
    "CVX":     "CVX_US_EQ",
    "COP":     "COP_US_EQ",
    "EOG":     "EOG_US_EQ",
    "MS":      "MS_US_EQ",
    "BLK":     "BLK_US_EQ",
    "NFLX":    "NFLX_US_EQ",
    "SBUX":    "SBUX_US_EQ",
    "MCD":     "MCD_US_EQ",
    "BA":      "BA_US_EQ",
    "RTX":     "RTX_US_EQ",
    "NOW":     "NOW_US_EQ",
    "ADBE":    "ADBE_US_EQ"
  },
  "_notes": "Maps yfinance tickers to Trading 212 internal tickers. Verify ETF tickers (VWCE, VUSA, VUKE) against T212 instruments endpoint after first connection."
}